sfu_ml_lib/__init__.py
sfu_ml_lib/base/__init__.py
sfu_ml_lib/base/dataset.py
sfu_ml_lib/base/metrics.py
sfu_ml_lib/base/tracker.py
sfu_ml_lib/common/__init__.py
sfu_ml_lib/common/math.py
sfu_ml_lib/common/shaping.py
sfu_ml_lib/common/sparse.py
sfu_ml_lib/dataset/__init__.py
sfu_ml_lib/dataset/balancing.py
sfu_ml_lib/dataset/batching.py
sfu_ml_lib/dataset/sparse.py
sfu_ml_lib/dataset/splitting.py
sfu_ml_lib/metrics/__init__.py
sfu_ml_lib/metrics/aggregation/__init__.py
sfu_ml_lib/metrics/aggregation/aggregations.py
sfu_ml_lib/metrics/aggregation/aggregator.py
sfu_ml_lib/metrics/aggregation/metric_functions.py
sfu_ml_lib/metrics/aggregator.py
sfu_ml_lib/metrics/cross_entropy.py
sfu_ml_lib/metrics/error.py
sfu_ml_lib/metrics/f1_score.py
sfu_ml_lib/metrics/mean.py
sfu_ml_lib/metrics/regression.py
sfu_ml_lib/models/__init__.py
sfu_ml_lib/models/callbacks.py
sfu_ml_lib/models/keras_model.py
sfu_ml_lib/modules/__init__.py
sfu_ml_lib/modules/attention.py
sfu_ml_lib/modules/encoders.py
sfu_ml_lib/trackers/__init__.py
sfu_ml_lib/trackers/mlflow.py
sfu_ml_lib/trackers/parameters.py
sfu_ml_lib-0.0.14.dist-info/LICENSE
sfu_ml_lib-0.0.14.dist-info/WHEEL
sfu_ml_lib-0.0.14.dist-info/METADATA
sfu_ml_lib-0.0.14.dist-info/RECORD
